<archimate:ArchimateDiagramModel
    xmlns:xsi="http://www.w3.org/2001/XMLSchema-instance"
    xmlns:archimate="http://www.archimatetool.com/archimate"
    name="03.Aplication Information Concept Model View"
    id="id-9ac11573306547eea46e94b7c5584fd8">
  <children
      xsi:type="archimate:DiagramModelArchimateObject"
      id="id-f4aea0a4701248499975cf38bbe4ae72"
      targetConnections="id-9c6d3bd1fce0447b860f0f47dcf9ed15"
      textPosition="1"
      type="1">
    <sourceConnections
        xsi:type="archimate:DiagramModelArchimateConnection"
        id="id-272f5ab761c541eca3c81b17d393c1e5"
        source="id-f4aea0a4701248499975cf38bbe4ae72"
        target="id-076a90cf73cf431794b1626f2ac9bb14">
      <archimateRelationship
          xsi:type="archimate:AggregationRelationship"
          href="AggregationRelationship_id-08d80715b76e4aae800779749a81cbd7.xml#id-08d80715b76e4aae800779749a81cbd7"/>
    </sourceConnections>
    <sourceConnections
        xsi:type="archimate:DiagramModelArchimateConnection"
        id="id-0e7748035b9d4c2a839ca0fe7a83928c"
        source="id-f4aea0a4701248499975cf38bbe4ae72"
        target="id-323e67f4bf0a450b812d3522e957ec64">
      <archimateRelationship
          xsi:type="archimate:CompositionRelationship"
          href="CompositionRelationship_id-b90dfc87f3434c0a953aa8ac5ac95537.xml#id-b90dfc87f3434c0a953aa8ac5ac95537"/>
    </sourceConnections>
    <sourceConnections
        xsi:type="archimate:DiagramModelArchimateConnection"
        id="id-f775b81e8bd5422a8394299c73e8e443"
        source="id-f4aea0a4701248499975cf38bbe4ae72"
        target="id-24014f6f37304827b871b58abff9dc00">
      <archimateRelationship
          xsi:type="archimate:AssociationRelationship"
          href="AssociationRelationship_id-bdbf82f11d984383821c1c35f6ffb53e.xml#id-bdbf82f11d984383821c1c35f6ffb53e"/>
    </sourceConnections>
    <bounds
        x="96"
        y="72"
        width="581"
        height="85"/>
    <archimateElement
        xsi:type="archimate:BusinessObject"
        href="BusinessObject_id-a0f679d5f9ca4316b04da6439bec4e0e.xml#id-a0f679d5f9ca4316b04da6439bec4e0e"/>
  </children>
  <children
      xsi:type="archimate:DiagramModelArchimateObject"
      id="id-076a90cf73cf431794b1626f2ac9bb14"
      targetConnections="id-272f5ab761c541eca3c81b17d393c1e5"
      textPosition="1"
      type="1">
    <bounds
        x="245"
        y="241"
        width="120"
        height="55"/>
    <archimateElement
        xsi:type="archimate:BusinessObject"
        href="BusinessObject_id-359937d84c934520a91c834c1696fd2e.xml#id-359937d84c934520a91c834c1696fd2e"/>
  </children>
  <children
      xsi:type="archimate:DiagramModelArchimateObject"
      id="id-323e67f4bf0a450b812d3522e957ec64"
      targetConnections="id-0e7748035b9d4c2a839ca0fe7a83928c"
      textPosition="1"
      type="1">
    <bounds
        x="96"
        y="241"
        width="120"
        height="55"/>
    <archimateElement
        xsi:type="archimate:BusinessObject"
        href="BusinessObject_id-2cf617a18e984d87aa5a6d653a9a62f0.xml#id-2cf617a18e984d87aa5a6d653a9a62f0"/>
  </children>
  <children
      xsi:type="archimate:DiagramModelArchimateObject"
      id="id-24014f6f37304827b871b58abff9dc00"
      targetConnections="id-f775b81e8bd5422a8394299c73e8e443"
      textPosition="1"
      type="1">
    <bounds
        x="401"
        y="241"
        width="120"
        height="55"/>
    <archimateElement
        xsi:type="archimate:BusinessObject"
        href="BusinessObject_id-061018ea4f0f4fdcbeca88b03fd36419.xml#id-061018ea4f0f4fdcbeca88b03fd36419"/>
  </children>
  <children
      xsi:type="archimate:DiagramModelArchimateObject"
      id="id-1f427812ac2f4e8a8ba053a236349b07"
      textPosition="1"
      type="1">
    <sourceConnections
        xsi:type="archimate:DiagramModelArchimateConnection"
        id="id-9c6d3bd1fce0447b860f0f47dcf9ed15"
        source="id-1f427812ac2f4e8a8ba053a236349b07"
        target="id-f4aea0a4701248499975cf38bbe4ae72">
      <archimateRelationship
          xsi:type="archimate:SpecializationRelationship"
          href="SpecializationRelationship_id-64e13bf813f74e71ad58b6304dcc7032.xml#id-64e13bf813f74e71ad58b6304dcc7032"/>
    </sourceConnections>
    <bounds
        x="557"
        y="241"
        width="120"
        height="55"/>
    <archimateElement
        xsi:type="archimate:BusinessObject"
        href="BusinessObject_id-44ffa636894b40968f48a1b3163e9e73.xml#id-44ffa636894b40968f48a1b3163e9e73"/>
  </children>
  <children
      xsi:type="archimate:DiagramModelNote"
      id="id-4271a3ab1d4e4bd1bc3090b88d6b9925"
      lineColor="#0080ff"
      content="Map to Data Governence Catalog"
      textPosition="1">
    <bounds
        x="312"
        y="360"
        width="185"
        height="80"/>
  </children>
  <children
      xsi:type="archimate:DiagramModelNote"
      id="id-e66b374cee0e416781e05ea7beed0784"
      textPosition="1"
      borderType="2">
    <features
        name="labelExpression"
        value="$view{property:Last Update}"/>
    <bounds
        x="587"
        y="33"
        width="185"
        height="34"/>
    <properties
        key="Last Update"
        value="Updated at 2021/5/13"/>
  </children>
  <children
      xsi:type="archimate:DiagramModelNote"
      id="id-7e0d7e8b1a4545f3b5096b6ae6f15ccd"
      font="1|Segoe UI|9.75|1|WINDOWS|1|-13|0|0|0|700|0|0|0|0|3|2|1|34|Segoe UI"
      textPosition="1"
      borderType="2">
    <features
        name="labelExpression"
        value="$view{name}"/>
    <bounds
        x="171"
        y="11"
        width="356"
        height="34"/>
  </children>
  <properties
      key="Last Update"
      value="Diagram Updated at 2022/3/23"/>
</archimate:ArchimateDiagramModel>
